[
  {
    "image": " Kôkô Dunda.png",
    "path": "/images/fabrics/studio/ Kôkô Dunda.png"
  },
  {
    "image": "Adinkra.png",
    "path": "/images/fabrics/studio/Adinkra.png"
  },
  {
    "image": "Adire.png",
    "path": "/images/fabrics/studio/Adire.png"
  },
  {
    "image": "Aso Oke.png",
    "path": "/images/fabrics/studio/Aso Oke.png"
  },
  {
    "image": "Batik malawien.png",
    "path": "/images/fabrics/studio/Batik malawien.png"
  },
  {
    "image": "Bazin riche.png",
    "path": "/images/fabrics/studio/Bazin riche.png"
  },
  {
    "image": "Bogolan.png",
    "path": "/images/fabrics/studio/Bogolan.png"
  },
  {
    "image": "Burnous.png",
    "path": "/images/fabrics/studio/Burnous.png"
  },
  {
    "image": "Caftan marocain.png",
    "path": "/images/fabrics/studio/Caftan marocain.png"
  },
  {
    "image": "Capulana.png",
    "path": "/images/fabrics/studio/Capulana.png"
  },
  {
    "image": "Chèche saharien.png",
    "path": "/images/fabrics/studio/Chèche saharien.png"
  },
  {
    "image": "Chiromani.png",
    "path": "/images/fabrics/studio/Chiromani.png"
  },
  {
    "image": "Chitenge.png",
    "path": "/images/fabrics/studio/Chitenge.png"
  },
  {
    "image": "Chitenje.png",
    "path": "/images/fabrics/studio/Chitenje.png"
  },
  {
    "image": "Écorce battue.png",
    "path": "/images/fabrics/studio/Écorce battue.png"
  },
  {
    "image": "Étoffe d’écorce .png",
    "path": "/images/fabrics/studio/Étoffe d’écorce .png"
  },
  {
    "image": "Étoffe d’écorce peinte (Mbuti) .png",
    "path": "/images/fabrics/studio/Étoffe d’écorce peinte (Mbuti) .png"
  },
  {
    "image": "Farrashia.png",
    "path": "/images/fabrics/studio/Farrashia.png"
  },
  {
    "image": "FasoDanFani.png",
    "path": "/images/fabrics/studio/FasoDanFani.png"
  },
  {
    "image": "Forêt sacrée.png",
    "path": "/images/fabrics/studio/Forêt sacrée.png"
  },
  {
    "image": "Futa(léfio).png",
    "path": "/images/fabrics/studio/Futa(léfio).png"
  },
  {
    "image": "Gabi.png",
    "path": "/images/fabrics/studio/Gabi.png"
  },
  {
    "image": "Galabeya(Djellabiya).png",
    "path": "/images/fabrics/studio/Galabeya(Djellabiya).png"
  },
  {
    "image": "Gara et pagne Manjak.png",
    "path": "/images/fabrics/studio/Gara et pagne Manjak.png"
  },
  {
    "image": "Gara.png",
    "path": "/images/fabrics/studio/Gara.png"
  },
  {
    "image": "Haïk.png",
    "path": "/images/fabrics/studio/Haïk.png"
  },
  {
    "image": "Imigongo.png",
    "path": "/images/fabrics/studio/Imigongo.png"
  },
  {
    "image": "Imvutano.png",
    "path": "/images/fabrics/studio/Imvutano.png"
  },
  {
    "image": "Jard (Houli).png",
    "path": "/images/fabrics/studio/Jard (Houli).png"
  },
  {
    "image": "Jebba.png",
    "path": "/images/fabrics/studio/Jebba.png"
  },
  {
    "image": "Kanga-leso.png",
    "path": "/images/fabrics/studio/Kanga-leso.png"
  },
  {
    "image": "Kanvô.png",
    "path": "/images/fabrics/studio/Kanvô.png"
  },
  {
    "image": "Karakou.png",
    "path": "/images/fabrics/studio/Karakou.png"
  },
  {
    "image": "Kente-ashanti.png",
    "path": "/images/fabrics/studio/Kente-ashanti.png"
  },
  {
    "image": "Kente.png",
    "path": "/images/fabrics/studio/Kente.png"
  },
  {
    "image": "Kenté.png",
    "path": "/images/fabrics/studio/Kenté.png"
  },
  {
    "image": "Kikoi.png",
    "path": "/images/fabrics/studio/Kikoi.png"
  },
  {
    "image": "Lamba landy.png",
    "path": "/images/fabrics/studio/Lamba landy.png"
  },
  {
    "image": "Lamba.png",
    "path": "/images/fabrics/studio/Lamba.png"
  },
  {
    "image": "Lamba1.png",
    "path": "/images/fabrics/studio/Lamba1.png"
  },
  {
    "image": "Lambahoany.png",
    "path": "/images/fabrics/studio/Lambahoany.png"
  },
  {
    "image": "Leso(Kanga mozambicain).png",
    "path": "/images/fabrics/studio/Leso(Kanga mozambicain).png"
  },
  {
    "image": "Lihiya (Emahiya).png",
    "path": "/images/fabrics/studio/Lihiya (Emahiya).png"
  },
  {
    "image": "Lubugo (Étoffe d’écorce).png",
    "path": "/images/fabrics/studio/Lubugo (Étoffe d’écorce).png"
  },
  {
    "image": "Macawis.png",
    "path": "/images/fabrics/studio/Macawis.png"
  },
  {
    "image": "Manjak.png",
    "path": "/images/fabrics/studio/Manjak.png"
  },
  {
    "image": "Mogagolwane.png",
    "path": "/images/fabrics/studio/Mogagolwane.png"
  },
  {
    "image": "Mutapa.png",
    "path": "/images/fabrics/studio/Mutapa.png"
  },
  {
    "image": "Ndop.png",
    "path": "/images/fabrics/studio/Ndop.png"
  },
  {
    "image": "Netela.png",
    "path": "/images/fabrics/studio/Netela.png"
  },
  {
    "image": "Obom(Libreville).png",
    "path": "/images/fabrics/studio/Obom(Libreville).png"
  },
  {
    "image": "Obom.png",
    "path": "/images/fabrics/studio/Obom.png"
  },
  {
    "image": "Ondelela.png",
    "path": "/images/fabrics/studio/Ondelela.png"
  },
  {
    "image": "Pagne Fang.png",
    "path": "/images/fabrics/studio/Pagne Fang.png"
  },
  {
    "image": "Pagne santoméen.png",
    "path": "/images/fabrics/studio/Pagne santoméen.png"
  },
  {
    "image": "Pano d'obra (pano di terra).png",
    "path": "/images/fabrics/studio/Pano d'obra (pano di terra).png"
  },
  {
    "image": "Raphia-okuyi.png.png",
    "path": "/images/fabrics/studio/Raphia-okuyi.png.png"
  },
  {
    "image": "Sabra.png",
    "path": "/images/fabrics/studio/Sabra.png"
  },
  {
    "image": "Sabra2.png",
    "path": "/images/fabrics/studio/Sabra2.png"
  },
  {
    "image": "Salouva.png",
    "path": "/images/fabrics/studio/Salouva.png"
  },
  {
    "image": "Samakaka.png",
    "path": "/images/fabrics/studio/Samakaka.png"
  },
  {
    "image": "Sanafil .png",
    "path": "/images/fabrics/studio/Sanafil .png"
  },
  {
    "image": "Seanamarena.png",
    "path": "/images/fabrics/studio/Seanamarena.png"
  },
  {
    "image": "Shamma(Érythrée).png",
    "path": "/images/fabrics/studio/Shamma(Érythrée).png"
  },
  {
    "image": "Shamma-3.png",
    "path": "/images/fabrics/studio/Shamma-3.png"
  },
  {
    "image": "Shamma.png",
    "path": "/images/fabrics/studio/Shamma.png"
  },
  {
    "image": "Shamma2.png",
    "path": "/images/fabrics/studio/Shamma2.png"
  },
  {
    "image": "Shuka masaï.png",
    "path": "/images/fabrics/studio/Shuka masaï.png"
  },
  {
    "image": "Shweshwe.png",
    "path": "/images/fabrics/studio/Shweshwe.png"
  },
  {
    "image": "Sidvwashi.png",
    "path": "/images/fabrics/studio/Sidvwashi.png"
  },
  {
    "image": "Strip-weave (pagne tissé).png",
    "path": "/images/fabrics/studio/Strip-weave (pagne tissé).png"
  },
  {
    "image": "Strip-weave (variation).png",
    "path": "/images/fabrics/studio/Strip-weave (variation).png"
  },
  {
    "image": "Tera-Tera.png",
    "path": "/images/fabrics/studio/Tera-Tera.png"
  },
  {
    "image": "Thioup (tie-dye).png",
    "path": "/images/fabrics/studio/Thioup (tie-dye).png"
  },
  {
    "image": "Thobe(Toub).png",
    "path": "/images/fabrics/studio/Thobe(Toub).png"
  },
  {
    "image": "Tissu de raphia.png",
    "path": "/images/fabrics/studio/Tissu de raphia.png"
  },
  {
    "image": "Toub.png",
    "path": "/images/fabrics/studio/Toub.png"
  },
  {
    "image": "Ujamani(Shweshwe namibien).png",
    "path": "/images/fabrics/studio/Ujamani(Shweshwe namibien).png"
  },
  {
    "image": "Umbhaco.png",
    "path": "/images/fabrics/studio/Umbhaco.png"
  },
  {
    "image": "Umushanana.png",
    "path": "/images/fabrics/studio/Umushanana.png"
  },
  {
    "image": "Velours-kasai.png",
    "path": "/images/fabrics/studio/Velours-kasai.png"
  },
  {
    "image": "Wax-Hollandais.png",
    "path": "/images/fabrics/studio/Wax-Hollandais.png"
  },
  {
    "image": "Zambia.png",
    "path": "/images/fabrics/studio/Zambia.png"
  },
  {
    "image": "Zanafi.png",
    "path": "/images/fabrics/studio/Zanafi.png"
  },
  {
    "image": "Zuria.png",
    "path": "/images/fabrics/studio/Zuria.png"
  },
  {
    "image": "hioup (variation).png",
    "path": "/images/fabrics/studio/hioup (variation).png"
  },
  {
    "image": "lusa Conjunta.png",
    "path": "/images/fabrics/studio/lusa Conjunta.png"
  },
  {
    "image": "raphia-wax.png",
    "path": "/images/fabrics/studio/raphia-wax.png"
  }
]